{
	"configurations" : 
	[
		{
			"directories" : 
			[
				{
					"build" : ".",
					"hasInstallRule" : true,
					"jsonFile" : "directory-.-4b2df197e73f5dbe7264.json",
					"minimumCMakeVersion" : 
					{
						"string" : "3.20"
					},
					"projectIndex" : 0,
					"source" : ".",
					"targetIndexes" : 
					[
						0,
						1,
						2,
						3
					]
				}
			],
			"name" : "",
			"projects" : 
			[
				{
					"directoryIndexes" : 
					[
						0
					],
					"name" : "turtlebot4_navigation",
					"targetIndexes" : 
					[
						0,
						1,
						2,
						3
					]
				}
			],
			"targets" : 
			[
				{
					"directoryIndex" : 0,
					"id" : "ament_cmake_python_build_turtlebot4_navigation_egg::@6890427a1f51a3e7e1df",
					"jsonFile" : "target-ament_cmake_python_build_turtlebot4_navigation_egg-a08ecb8ed741a367dfcb.json",
					"name" : "ament_cmake_python_build_turtlebot4_navigation_egg",
					"projectIndex" : 0
				},
				{
					"directoryIndex" : 0,
					"id" : "ament_cmake_python_symlink_turtlebot4_navigation::@6890427a1f51a3e7e1df",
					"jsonFile" : "target-ament_cmake_python_symlink_turtlebot4_navigation-b2a6a90c3e27c25761b5.json",
					"name" : "ament_cmake_python_symlink_turtlebot4_navigation",
					"projectIndex" : 0
				},
				{
					"directoryIndex" : 0,
					"id" : "turtlebot4_navigation_uninstall::@6890427a1f51a3e7e1df",
					"jsonFile" : "target-turtlebot4_navigation_uninstall-e0e2fdccdf4a9fd87aad.json",
					"name" : "turtlebot4_navigation_uninstall",
					"projectIndex" : 0
				},
				{
					"directoryIndex" : 0,
					"id" : "uninstall::@6890427a1f51a3e7e1df",
					"jsonFile" : "target-uninstall-4e468bb778064e8f793e.json",
					"name" : "uninstall",
					"projectIndex" : 0
				}
			]
		}
	],
	"kind" : "codemodel",
	"paths" : 
	{
		"build" : "/home/feiying/ros2_learn/L05_turtlebot4/build/turtlebot4_navigation",
		"source" : "/home/feiying/ros2_learn/L05_turtlebot4/src/turtlebot4/turtlebot4_navigation"
	},
	"version" : 
	{
		"major" : 2,
		"minor" : 6
	}
}
